extract_subtitles/__init__.py
extract_subtitles/extract_subtitles.py
transcribe_subtitles/transcribe_subtitles.py
translate_subtitles/__init__.py
translate_subtitles/translate_subtitles.py
video_translator-0.0.2.dist-info/LICENSE
video_translator-0.0.2.dist-info/METADATA
video_translator-0.0.2.dist-info/WHEEL
video_translator-0.0.2.dist-info/entry_points.txt
video_translator-0.0.2.dist-info/top_level.txt
video_translator-0.0.2.dist-info/RECORD
